[
  {
    "Hospital_ID": 1,
    "Hospital_Name": "Appling Hospital",
    "Street_Address": "163 E Tollison St",
    "City": "Baxley",
    "State": "GA",
    "ZIP_Code": "31513",
    "County": "Appling",
    "County_FIPS": "13001",
    "Latitude": 33.54609,
    "Longitude": -82.3163154,
    "Urban_Rural": "Rural",
    "In_System": 0,
    "System_Name": "Appling Healthcare",
    "Ownership_Type": "Government",
    "Care_Level": "Primary",
    "Bed_Size": 64,
    "Size_Group": "S",
    "Hospital_URL": "https://www.applinghealthcare.org",
    "Balance_Growth": 4,
    "Transparency": 4,
    "Fiscal_Health": 3,
    "Staffing": 4,
    "FTIH_Category_Rating": 4,
    "Tax_Benefit": 3,
    "Quality_of_CBS": 3,
    "Strategic_Use": 4,
    "CBS_Category_Rating": 4,
    "Financial_Burden": 3,
    "Charity_Care": 3,
    "Medical_Debt": 3,
    "HAB_Category_Rating": 4,
    "Range_of_Services": 3,
    "Demographic_Alignment": 4,
    "Workforce_Training": 3,
    "Pay_Equity_Ratio": 4,
    "HASR_Category_Rating": 4,
    "Overall_Star_Rating": 3,
    "Services_Offered": "Emergency Care\nImaging & Radiology\nOutpatient Surgery\nPharmacy\nPhysical Therapy\nRehabilitation"
  },
  {
    "Hospital_ID": 2,
    "Hospital_Name": "Bacon County Hospital",
    "Street_Address": "302 S Wayne St",
    "City": "Alma",
    "State": "GA",
    "ZIP_Code": "31510",
    "County": "Bacon",
    "County_FIPS": "13005",
    "Latitude": 31.538626,
    "Longitude": -82.459238,
    "Urban_Rural": "Rural",
    "In_System": 0,
    "System_Name": "Bacon County Hospital and Health System",
    "Ownership_Type": "Government",
    "Care_Level": "Primary",
    "Bed_Size": 25,
    "Size_Group": "S",
    "Hospital_URL": "https://www.baconcountyhospital.com",
    "Balance_Growth": 3,
    "Transparency": 4,
    "Fiscal_Health": 3,
    "Staffing": 3,
    "FTIH_Category_Rating": 3,
    "Tax_Benefit": 3,
    "Quality_of_CBS": 3,
    "Strategic_Use": 3,
    "CBS_Category_Rating": 3,
    "Financial_Burden": 3,
    "Charity_Care": 3,
    "Medical_Debt": 3,
    "HAB_Category_Rating": 3,
    "Range_of_Services": 3,
    "Demographic_Alignment": 3,
    "Workforce_Training": 3,
    "Pay_Equity_Ratio": 3,
    "HASR_Category_Rating": 3,
    "Overall_Star_Rating": 3,
    "Services_Offered": "Emergency Care\nImaging & Radiology\nPharmacy\nPhysical Therapy\nRehabilitation"
  },
  {
    "Hospital_ID": 3,
    "Hospital_Name": "Burke Medical Center",
    "Street_Address": "351 S Liberty St",
    "City": "Waynesboro",
    "State": "GA",
    "ZIP_Code": "30830",
    "County": "Burke",
    "County_FIPS": "13033",
    "Latitude": 33.0833,
    "Longitude": -82.0134,
    "Urban_Rural": "Urban",
    "In_System": 0,
    "System_Name": "Burke Health",
    "Ownership_Type": "Government",
    "Care_Level": "Primary",
    "Bed_Size": 40,
    "Size_Group": "S",
    "Hospital_URL": "https://www.burkemedicalcenter.com",
    "Balance_Growth": 3,
    "Transparency": 4,
    "Fiscal_Health": 3,
    "Staffing": 3,
    "FTIH_Category_Rating": 3,
    "Tax_Benefit": 3,
    "Quality_of_CBS": 3,
    "Strategic_Use": 3,
    "CBS_Category_Rating": 3,
    "Financial_Burden": 3,
    "Charity_Care": 3,
    "Medical_Debt": 3,
    "HAB_Category_Rating": 3,
    "Range_of_Services": 3,
    "Demographic_Alignment": 3,
    "Workforce_Training": 3,
    "Pay_Equity_Ratio": 3,
    "HASR_Category_Rating": 3,
    "Overall_Star_Rating": 3,
    "Services_Offered": "Cardiology\nEmergency Care\nImaging & Radiology\nOrthopedics\nOutpatient Surgery\nPharmacy\nPhysical Therapy\nRehabilitation"
  },
  {
    "Hospital_ID": 5,
    "Hospital_Name": "Piedmont Hospital",
    "Street_Address": "1968 Peachtree Rd NW",
    "City": "Atlanta",
    "State": "GA",
    "ZIP_Code": "30309",
    "County": "Fulton",
    "County_FIPS": "13121",
    "Latitude": 33.80915,
    "Longitude": -84.39547,
    "Urban_Rural": "Urban",
    "In_System": 1,
    "System_Name": "Piedmont Healthcare",
    "Ownership_Type": "Nonprofit",
    "Care_Level": "Regional Referral",
    "Bed_Size": 643,
    "Size_Group": "XXL",
    "Hospital_URL": "https://www.piedmont.org/locations/piedmont-atlanta",
    "Balance_Growth": 5,
    "Transparency": 5,
    "Fiscal_Health": 4,
    "Staffing": 4,
    "FTIH_Category_Rating": 5,
    "Tax_Benefit": 4,
    "Quality_of_CBS": 4,
    "Strategic_Use": 4,
    "CBS_Category_Rating": 4,
    "Financial_Burden": 3,
    "Charity_Care": 4,
    "Medical_Debt": 3,
    "HAB_Category_Rating": 4,
    "Range_of_Services": 4,
    "Demographic_Alignment": 4,
    "Workforce_Training": 4,
    "Pay_Equity_Ratio": 4,
    "HASR_Category_Rating": 4,
    "Overall_Star_Rating": 4,
    "Services_Offered": "Behavioral Health\nCardiology\nEmergency Care\nImaging & Radiology\nMaternity & Neonatal ICU\nOncology\nOrthopedics\nOutpatient Surgery\nPediatric Services\nPharmacy\nPhysical Therapy\nRehabilitation"
  },
  {
    "Hospital_ID": 6,
    "Hospital_Name": "Phoebe Putney Memorial Hospital",
    "Street_Address": "417 W 3rd Ave",
    "City": "Albany",
    "State": "GA",
    "ZIP_Code": "31701",
    "County": "Dougherty",
    "County_FIPS": "13095",
    "Latitude": 31.59022,
    "Longitude": -84.15779,
    "Urban_Rural": "Urban",
    "In_System": 1,
    "System_Name": "Phoebe Putney Health System",
    "Ownership_Type": "Nonprofit",
    "Care_Level": "Regional Referral",
    "Bed_Size": 691,
    "Size_Group": "XXL",
    "Hospital_URL": "https://www.phoebehealth.com",
    "Balance_Growth": 4,
    "Transparency": 4,
    "Fiscal_Health": 4,
    "Staffing": 4,
    "FTIH_Category_Rating": 4,
    "Tax_Benefit": 3,
    "Quality_of_CBS": 3,
    "Strategic_Use": 4,
    "CBS_Category_Rating": 4,
    "Financial_Burden": 3,
    "Charity_Care": 3,
    "Medical_Debt": 3,
    "HAB_Category_Rating": 4,
    "Range_of_Services": 4,
    "Demographic_Alignment": 4,
    "Workforce_Training": 4,
    "Pay_Equity_Ratio": 4,
    "HASR_Category_Rating": 4,
    "Overall_Star_Rating": 4,
    "Services_Offered": "Behavioral Health\nCardiology\nEmergency Care\nImaging & Radiology\nMaternity & Neonatal ICU\nOncology\nOrthopedics\nOutpatient SurgeryPediatric Services\nPharmacy\nPhysical Therapy\nRehabilitation"
  },
  {
    "Hospital_ID": 7,
    "Hospital_Name": "Northside Hospital Atlanta",
    "Street_Address": "1000 Johnson Ferry Rd NE",
    "City": "Atlanta",
    "State": "GA",
    "ZIP_Code": "30342",
    "County": "Fulton",
    "County_FIPS": "13121",
    "Latitude": 33.908404,
    "Longitude": -84.354543,
    "Urban_Rural": "Urban",
    "In_System": 1,
    "System_Name": "Northside Hospital",
    "Ownership_Type": "Nonprofit",
    "Care_Level": "Regional Referral",
    "Bed_Size": 685,
    "Size_Group": "XXL",
    "Hospital_URL": "https://www.northside.com/locations/atlanta",
    "Balance_Growth": 5,
    "Transparency": 4,
    "Fiscal_Health": 4,
    "Staffing": 5,
    "FTIH_Category_Rating": 5,
    "Tax_Benefit": 3,
    "Quality_of_CBS": 4,
    "Strategic_Use": 4,
    "CBS_Category_Rating": 4,
    "Financial_Burden": 3,
    "Charity_Care": 3,
    "Medical_Debt": 3,
    "HAB_Category_Rating": 4,
    "Range_of_Services": 4,
    "Demographic_Alignment": 4,
    "Workforce_Training": 4,
    "Pay_Equity_Ratio": 5,
    "HASR_Category_Rating": 4,
    "Overall_Star_Rating": 4,
    "Services_Offered": "Behavioral Health\nCardiology\nEmergency Care\nImaging & Radiology\nMaternity & Neonatal ICU\nOncology\nOrthopedics\nOutpatient Surgery\nPediatric Services\nPharmacy\nPhysical Therapy\nRehabilitation"
  },
  {
    "Hospital_ID": 8,
    "Hospital_Name": "Tanner Medical Center \u2013 Villa Rica",
    "Street_Address": "601 Dallas Hwy",
    "City": "Villa Rica",
    "State": "GA",
    "ZIP_Code": "30180",
    "County": "Carroll",
    "County_FIPS": "13045",
    "Latitude": 33.56995,
    "Longitude": -85.07421,
    "Urban_Rural": "Urban",
    "In_System": 1,
    "System_Name": "Tanner Health System",
    "Ownership_Type": "Nonprofit",
    "Care_Level": "Specialty",
    "Bed_Size": 53,
    "Size_Group": "S",
    "Hospital_URL": "https://www.tanner.org",
    "Balance_Growth": 4,
    "Transparency": 4,
    "Fiscal_Health": 3,
    "Staffing": 4,
    "FTIH_Category_Rating": 4,
    "Tax_Benefit": 3,
    "Quality_of_CBS": 3,
    "Strategic_Use": 3,
    "CBS_Category_Rating": 3,
    "Financial_Burden": 3,
    "Charity_Care": 3,
    "Medical_Debt": 3,
    "HAB_Category_Rating": 3,
    "Range_of_Services": 3,
    "Demographic_Alignment": 3,
    "Workforce_Training": 3,
    "Pay_Equity_Ratio": 3,
    "HASR_Category_Rating": 3,
    "Overall_Star_Rating": 3,
    "Services_Offered": "Behavioral Health\nCardiology\nEmergency Care\nImaging & Radiology\nMaternity & Neonatal ICU\nOncology\nOrthopedics\nOutpatient Surgery\nPediatric Services Pharmacy\nPhysical Therapy\nRehabilitation"
  },
  {
    "Hospital_ID": 9,
    "Hospital_Name": "Emory University Hospital",
    "Street_Address": "1364 Clifton Rd NE",
    "City": "Atlanta",
    "State": "GA",
    "ZIP_Code": "30322",
    "County": "DeKalb",
    "County_FIPS": "13089",
    "Latitude": 33.7954,
    "Longitude": -84.3202,
    "Urban_Rural": "Urban",
    "In_System": 1,
    "System_Name": "Emory Healthcare",
    "Ownership_Type": "Nonprofit",
    "Care_Level": "Regional Referral",
    "Bed_Size": 733,
    "Size_Group": "XXL",
    "Hospital_URL": "https://www.emoryhealthcare.org",
    "Balance_Growth": 5,
    "Transparency": 5,
    "Fiscal_Health": 5,
    "Staffing": 5,
    "FTIH_Category_Rating": 5,
    "Tax_Benefit": 4,
    "Quality_of_CBS": 4,
    "Strategic_Use": 5,
    "CBS_Category_Rating": 5,
    "Financial_Burden": 4,
    "Charity_Care": 4,
    "Medical_Debt": 4,
    "HAB_Category_Rating": 5,
    "Range_of_Services": 5,
    "Demographic_Alignment": 5,
    "Workforce_Training": 5,
    "Pay_Equity_Ratio": 5,
    "HASR_Category_Rating": 5,
    "Overall_Star_Rating": 4,
    "Services_Offered": "Emergency Care\nCardiology\nImaging & Radiology\nOncology\nMaternity & Neonatal ICU\nOrthopedics\nOutpatient Surgery\nPharmacy\nPhysical Therapy\nRehabilitation\nPediatric Services\nBehavioral Health"
  },
  {
    "Hospital_ID": 10,
    "Hospital_Name": "St. Mary's Hospital",
    "Street_Address": "1230 Baxter St",
    "City": "Athens",
    "State": "GA",
    "ZIP_Code": "30606",
    "County": "Clarke",
    "County_FIPS": "13059",
    "Latitude": 34.16608,
    "Longitude": -83.4013,
    "Urban_Rural": "Urban",
    "In_System": 1,
    "System_Name": "St. Mary's Healthcare System",
    "Ownership_Type": "Nonprofit",
    "Care_Level": "Regional Referral",
    "Bed_Size": 196,
    "Size_Group": "L",
    "Hospital_URL": "https://www.stmaryshealthcaresystem.org",
    "Balance_Growth": 4,
    "Transparency": 4,
    "Fiscal_Health": 4,
    "Staffing": 4,
    "FTIH_Category_Rating": 4,
    "Tax_Benefit": 3,
    "Quality_of_CBS": 4,
    "Strategic_Use": 4,
    "CBS_Category_Rating": 4,
    "Financial_Burden": 3,
    "Charity_Care": 3,
    "Medical_Debt": 3,
    "HAB_Category_Rating": 4,
    "Range_of_Services": 4,
    "Demographic_Alignment": 4,
    "Workforce_Training": 4,
    "Pay_Equity_Ratio": 4,
    "HASR_Category_Rating": 4,
    "Overall_Star_Rating": 4,
    "Services_Offered": "Behavioral Health\nCardiology Emergency Care\nImaging & Radiology\nMaternity & Neonatal ICU\nOncology\nOrthopedics\nOutpatient Surgery\nPediatric Services\nPharmacy\nPhysical Therapy\nRehabilitation"
  },
  {
    "Hospital_ID": 11,
    "Hospital_Name": "Wellstar Kennestone Hospital",
    "Street_Address": "677 Church St NE",
    "City": "Marietta",
    "State": "GA",
    "ZIP_Code": "30060",
    "County": "Cobb",
    "County_FIPS": "13067",
    "Latitude": 33.96795,
    "Longitude": -84.55135,
    "Urban_Rural": "Urban",
    "In_System": 1,
    "System_Name": "Wellstar Health System",
    "Ownership_Type": "Nonprofit",
    "Care_Level": "Regional Referral",
    "Bed_Size": 633,
    "Size_Group": "XXL",
    "Hospital_URL": "https://www.wellstar.org",
    "Balance_Growth": 5,
    "Transparency": 4,
    "Fiscal_Health": 4,
    "Staffing": 5,
    "FTIH_Category_Rating": 5,
    "Tax_Benefit": 4,
    "Quality_of_CBS": 4,
    "Strategic_Use": 4,
    "CBS_Category_Rating": 4,
    "Financial_Burden": 3,
    "Charity_Care": 4,
    "Medical_Debt": 3,
    "HAB_Category_Rating": 4,
    "Range_of_Services": 4,
    "Demographic_Alignment": 4,
    "Workforce_Training": 4,
    "Pay_Equity_Ratio": 4,
    "HASR_Category_Rating": 4,
    "Overall_Star_Rating": 4,
    "Services_Offered": "Behavioral Health\nCardiology\nEmergency Care\nImaging & Radiology\nMaternity & Neonatal ICU\nOncology\nOrthopedics\nOutpatient Surgery\nPediatric Services\nPharmacy\nPhysical Therapy\nRehabilitation"
  },
  {
    "Hospital_ID": 12,
    "Hospital_Name": "Candler County Hospital",
    "Street_Address": "400 Cedar St",
    "City": "Metter",
    "State": "GA",
    "ZIP_Code": "30439",
    "County": "Candler",
    "County_FIPS": "13043",
    "Latitude": 32.0809,
    "Longitude": -81.0912,
    "Urban_Rural": "Urban",
    "In_System": 0,
    "System_Name": "Candler County Hospital Authority",
    "Ownership_Type": "Nonprofit",
    "Care_Level": "Primary",
    "Bed_Size": 25,
    "Size_Group": "S",
    "Hospital_URL": "https://www.google.com/search?q=Candler+County+Hospital+Metter+GA+hospital",
    "Balance_Growth": 4,
    "Transparency": 3,
    "Fiscal_Health": 4,
    "Staffing": 4,
    "FTIH_Category_Rating": 5,
    "Tax_Benefit": 5,
    "Quality_of_CBS": 3,
    "Strategic_Use": 4,
    "CBS_Category_Rating": 4,
    "Financial_Burden": 5,
    "Charity_Care": 5,
    "Medical_Debt": 5,
    "HAB_Category_Rating": 4,
    "Range_of_Services": 3,
    "Demographic_Alignment": 4,
    "Workforce_Training": 5,
    "Pay_Equity_Ratio": 3,
    "HASR_Category_Rating": 5,
    "Overall_Star_Rating": 3,
    "Services_Offered": "Emergency Care\nImaging & Radiology\nOutpatient Surgery\nPharmacy\nPhysical Therapy\nRehabilitation"
  },
  {
    "Hospital_ID": 13,
    "Hospital_Name": "Clinch Memorial Hospital",
    "Street_Address": "1050 Valdosta Hwy",
    "City": "Homerville",
    "State": "GA",
    "ZIP_Code": "31634",
    "County": "Clinch",
    "County_FIPS": "13113",
    "Latitude": 31.0339,
    "Longitude": -82.76445,
    "Urban_Rural": "Urban",
    "In_System": 0,
    "System_Name": "South Georgia Medical Center",
    "Ownership_Type": "Nonprofit",
    "Care_Level": "Primary",
    "Bed_Size": 25,
    "Size_Group": "S",
    "Hospital_URL": "https://www.google.com/search?q=Clinch+Memorial+Hospital+Homerville+GA+hospital",
    "Balance_Growth": 4,
    "Transparency": 4,
    "Fiscal_Health": 4,
    "Staffing": 5,
    "FTIH_Category_Rating": 3,
    "Tax_Benefit": 4,
    "Quality_of_CBS": 5,
    "Strategic_Use": 5,
    "CBS_Category_Rating": 4,
    "Financial_Burden": 3,
    "Charity_Care": 5,
    "Medical_Debt": 4,
    "HAB_Category_Rating": 4,
    "Range_of_Services": 5,
    "Demographic_Alignment": 5,
    "Workforce_Training": 3,
    "Pay_Equity_Ratio": 5,
    "HASR_Category_Rating": 3,
    "Overall_Star_Rating": 4,
    "Services_Offered": "Emergency Care\nImaging & Radiology\nOutpatient Surgery\nPharmacy\nPhysical Therapy\nRehabilitation"
  },
  {
    "Hospital_ID": 14,
    "Hospital_Name": "Coffee Regional Medical Center",
    "Street_Address": "1101 Ocila Road",
    "City": "Douglas",
    "State": "GA",
    "ZIP_Code": "31533",
    "County": "Coffee",
    "County_FIPS": "13159",
    "Latitude": 31.5047,
    "Longitude": -82.8586,
    "Urban_Rural": "Urban",
    "In_System": 0,
    "System_Name": "Coffee Regional Medical Center",
    "Ownership_Type": "Nonprofit",
    "Care_Level": "Primary",
    "Bed_Size": 82,
    "Size_Group": "S",
    "Hospital_URL": "https://www.google.com/search?q=Coffee+Regional+Medical+Center+Douglas+GA+hospital",
    "Balance_Growth": 3,
    "Transparency": 3,
    "Fiscal_Health": 3,
    "Staffing": 3,
    "FTIH_Category_Rating": 5,
    "Tax_Benefit": 3,
    "Quality_of_CBS": 4,
    "Strategic_Use": 5,
    "CBS_Category_Rating": 4,
    "Financial_Burden": 3,
    "Charity_Care": 3,
    "Medical_Debt": 4,
    "HAB_Category_Rating": 4,
    "Range_of_Services": 3,
    "Demographic_Alignment": 4,
    "Workforce_Training": 5,
    "Pay_Equity_Ratio": 4,
    "HASR_Category_Rating": 4,
    "Overall_Star_Rating": 5,
    "Services_Offered": "Cardiology\nEmergency Care\nImaging & Radiology\nMaternity & Neonatal ICU\nOncology\nOrthopedics\nOutpatient Surgery Pediatric Services\nPharmacy\nPhysical Therapy\nRehabilitation"
  },
  {
    "Hospital_ID": 15,
    "Hospital_Name": "Colquitt Regional Medical Center",
    "Street_Address": "3131 S Main St",
    "City": "Moultrie",
    "State": "GA",
    "ZIP_Code": "31768",
    "County": "Colquitt",
    "County_FIPS": "13071",
    "Latitude": 31.1621,
    "Longitude": -83.7921,
    "Urban_Rural": "Urban",
    "In_System": 0,
    "System_Name": "Colquitt Regional Health System",
    "Ownership_Type": "Nonprofit",
    "Care_Level": "Specialty",
    "Bed_Size": 155,
    "Size_Group": "L",
    "Hospital_URL": "https://www.google.com/search?q=Colquitt+Regional+Medical+Center+Moultrie+GA+hospital",
    "Balance_Growth": 4,
    "Transparency": 4,
    "Fiscal_Health": 3,
    "Staffing": 4,
    "FTIH_Category_Rating": 4,
    "Tax_Benefit": 3,
    "Quality_of_CBS": 5,
    "Strategic_Use": 3,
    "CBS_Category_Rating": 3,
    "Financial_Burden": 5,
    "Charity_Care": 3,
    "Medical_Debt": 5,
    "HAB_Category_Rating": 3,
    "Range_of_Services": 5,
    "Demographic_Alignment": 3,
    "Workforce_Training": 3,
    "Pay_Equity_Ratio": 3,
    "HASR_Category_Rating": 5,
    "Overall_Star_Rating": 3,
    "Services_Offered": "Behavioral Health\nCardiology\nEmergency Care\nImaging & Radiology\nMaternity & Neonatal ICU\nOncology\nOrthopedics\nOutpatient Surgery\nPediatric Services\nPharmacy\nPhysical Therapy\nRehabilitation"
  },
  {
    "Hospital_ID": 16,
    "Hospital_Name": "Crisp Regional Hospital",
    "Street_Address": "902 7th St N",
    "City": "Cordele",
    "State": "GA",
    "ZIP_Code": "31015",
    "County": "Crisp",
    "County_FIPS": "13191",
    "Latitude": 31.97761,
    "Longitude": -83.781268,
    "Urban_Rural": "Urban",
    "In_System": 0,
    "System_Name": "Crisp Regional Health Services",
    "Ownership_Type": "Nonprofit",
    "Care_Level": "Specialty",
    "Bed_Size": 211,
    "Size_Group": "XL",
    "Hospital_URL": "https://www.google.com/search?q=Crisp+Regional+Hospital+Cordele+GA+hospital",
    "Balance_Growth": 3,
    "Transparency": 5,
    "Fiscal_Health": 3,
    "Staffing": 5,
    "FTIH_Category_Rating": 3,
    "Tax_Benefit": 3,
    "Quality_of_CBS": 4,
    "Strategic_Use": 3,
    "CBS_Category_Rating": 4,
    "Financial_Burden": 3,
    "Charity_Care": 5,
    "Medical_Debt": 4,
    "HAB_Category_Rating": 4,
    "Range_of_Services": 5,
    "Demographic_Alignment": 3,
    "Workforce_Training": 3,
    "Pay_Equity_Ratio": 3,
    "HASR_Category_Rating": 5,
    "Overall_Star_Rating": 4,
    "Services_Offered": "Behavioral Health\nCardiology\nEmergency Care\nImaging & Radiology\nMaternity & Neonatal ICU\nOncology\nOrthopedics\nOutpatient Surgery\nPediatric Services\nPharmacy\nPhysical Therapy\nRehabilitation"
  },
  {
    "Hospital_ID": 17,
    "Hospital_Name": "Dodge County Hospital",
    "Street_Address": "901 Griffin Ave",
    "City": "Eastman",
    "State": "GA",
    "ZIP_Code": "31023",
    "County": "Dodge",
    "County_FIPS": "13091",
    "Latitude": 32.18507,
    "Longitude": -83.17896,
    "Urban_Rural": "Urban",
    "In_System": 0,
    "System_Name": "Dodge County Hospital",
    "Ownership_Type": "Nonprofit",
    "Care_Level": "Primary",
    "Bed_Size": 94,
    "Size_Group": "S",
    "Hospital_URL": "https://www.google.com/search?q=Dodge+County+Hospital+Eastman+GA+hospital",
    "Balance_Growth": 4,
    "Transparency": 3,
    "Fiscal_Health": 4,
    "Staffing": 5,
    "FTIH_Category_Rating": 5,
    "Tax_Benefit": 4,
    "Quality_of_CBS": 4,
    "Strategic_Use": 3,
    "CBS_Category_Rating": 5,
    "Financial_Burden": 3,
    "Charity_Care": 3,
    "Medical_Debt": 3,
    "HAB_Category_Rating": 3,
    "Range_of_Services": 4,
    "Demographic_Alignment": 3,
    "Workforce_Training": 5,
    "Pay_Equity_Ratio": 4,
    "HASR_Category_Rating": 4,
    "Overall_Star_Rating": 4,
    "Services_Offered": "Emergency Care\nImaging & Radiology\nOutpatient Surgery\nPharmacy\nPhysical Therapy\nRehabilitation"
  },
  {
    "Hospital_ID": 18,
    "Hospital_Name": "Donalsonville Hospital, Inc.",
    "Street_Address": "102 Hospital Circle",
    "City": "Donalsonville",
    "State": "GA",
    "ZIP_Code": "39845",
    "County": "Seminole",
    "County_FIPS": "13135",
    "Latitude": 31.05102,
    "Longitude": -84.88167,
    "Urban_Rural": "Urban",
    "In_System": 0,
    "System_Name": "Donalsonville Hospital, Inc.",
    "Ownership_Type": "Nonprofit",
    "Care_Level": "Primary",
    "Bed_Size": 61,
    "Size_Group": "S",
    "Hospital_URL": "https://www.google.com/search?q=Donalsonville+Hospital,+Inc.+Donalsonville+GA+hospital",
    "Balance_Growth": 4,
    "Transparency": 3,
    "Fiscal_Health": 5,
    "Staffing": 5,
    "FTIH_Category_Rating": 5,
    "Tax_Benefit": 3,
    "Quality_of_CBS": 3,
    "Strategic_Use": 4,
    "CBS_Category_Rating": 5,
    "Financial_Burden": 3,
    "Charity_Care": 3,
    "Medical_Debt": 3,
    "HAB_Category_Rating": 4,
    "Range_of_Services": 5,
    "Demographic_Alignment": 4,
    "Workforce_Training": 5,
    "Pay_Equity_Ratio": 5,
    "HASR_Category_Rating": 4,
    "Overall_Star_Rating": 5,
    "Services_Offered": "Emergency Care\nImaging & Radiology\nOutpatient Surgery\nPharmacy\nPhysical Therapy\nRehabilitation"
  },
  {
    "Hospital_ID": 19,
    "Hospital_Name": "Dorminy Medical Center",
    "Street_Address": "200 Perry House Rd",
    "City": "Fitzgerald",
    "State": "GA",
    "ZIP_Code": "31750",
    "County": "Ben Hill",
    "County_FIPS": "13019",
    "Latitude": 31.69762,
    "Longitude": -83.25991,
    "Urban_Rural": "Urban",
    "In_System": 0,
    "System_Name": "Dorminy Medical Center",
    "Ownership_Type": "Nonprofit",
    "Care_Level": "Primary",
    "Bed_Size": 75,
    "Size_Group": "S",
    "Hospital_URL": "https://www.google.com/search?q=Dorminy+Medical+Center+Fitzgerald+GA+hospital",
    "Balance_Growth": 3,
    "Transparency": 3,
    "Fiscal_Health": 3,
    "Staffing": 4,
    "FTIH_Category_Rating": 5,
    "Tax_Benefit": 4,
    "Quality_of_CBS": 5,
    "Strategic_Use": 4,
    "CBS_Category_Rating": 3,
    "Financial_Burden": 4,
    "Charity_Care": 5,
    "Medical_Debt": 3,
    "HAB_Category_Rating": 3,
    "Range_of_Services": 5,
    "Demographic_Alignment": 3,
    "Workforce_Training": 4,
    "Pay_Equity_Ratio": 5,
    "HASR_Category_Rating": 4,
    "Overall_Star_Rating": 4,
    "Services_Offered": "Cardiology\nEmergency Care\nImaging & Radiology\nMaternity & Neonatal ICU\nOrthopedics\nOutpatient Surgery\nPharmacy\nPhysical Therapy\nRehabilitation"
  },
  {
    "Hospital_ID": 20,
    "Hospital_Name": "East Georgia Regional Medical Center",
    "Street_Address": "1499 Fair Rd",
    "City": "Statesboro",
    "State": "GA",
    "ZIP_Code": "30458",
    "County": "Bulloch",
    "County_FIPS": "13031",
    "Latitude": 32.4488,
    "Longitude": -81.7832,
    "Urban_Rural": "Urban",
    "In_System": 0,
    "System_Name": "Community Health Systems",
    "Ownership_Type": "Nonprofit",
    "Care_Level": "Primary",
    "Bed_Size": 142,
    "Size_Group": "L",
    "Hospital_URL": "https://www.google.com/search?q=East+Georgia+Regional+Medical+Center+Statesboro+GA+hospital",
    "Balance_Growth": 5,
    "Transparency": 5,
    "Fiscal_Health": 5,
    "Staffing": 4,
    "FTIH_Category_Rating": 4,
    "Tax_Benefit": 4,
    "Quality_of_CBS": 5,
    "Strategic_Use": 5,
    "CBS_Category_Rating": 3,
    "Financial_Burden": 4,
    "Charity_Care": 4,
    "Medical_Debt": 5,
    "HAB_Category_Rating": 3,
    "Range_of_Services": 5,
    "Demographic_Alignment": 4,
    "Workforce_Training": 5,
    "Pay_Equity_Ratio": 3,
    "HASR_Category_Rating": 5,
    "Overall_Star_Rating": 4,
    "Services_Offered": "Cardiology\nEmergency Care\nImaging & Radiology\nMaternity & Neonatal ICU\nOncology\nOrthopedics\nOutpatient Surgery\nPediatric Services\nPharmacy\nPhysical Therapy\nRehabilitation"
  },
  {
    "Hospital_ID": 21,
    "Hospital_Name": "Effingham Health System",
    "Street_Address": "459 GA-119",
    "City": "Springfield",
    "State": "GA",
    "ZIP_Code": "31329",
    "County": "Effingham County",
    "County_FIPS": "13103",
    "Latitude": 32.36369,
    "Longitude": -81.32069,
    "Urban_Rural": "Urban",
    "In_System": 0,
    "System_Name": "Effingham Health System",
    "Ownership_Type": "Nonprofit",
    "Care_Level": "Primary",
    "Bed_Size": 25,
    "Size_Group": "S",
    "Hospital_URL": "https://www.google.com/search?q=Effingham+Health+System+Springfield+GA+hospital",
    "Balance_Growth": 3,
    "Transparency": 5,
    "Fiscal_Health": 4,
    "Staffing": 5,
    "FTIH_Category_Rating": 5,
    "Tax_Benefit": 5,
    "Quality_of_CBS": 4,
    "Strategic_Use": 5,
    "CBS_Category_Rating": 4,
    "Financial_Burden": 5,
    "Charity_Care": 5,
    "Medical_Debt": 4,
    "HAB_Category_Rating": 4,
    "Range_of_Services": 3,
    "Demographic_Alignment": 4,
    "Workforce_Training": 3,
    "Pay_Equity_Ratio": 5,
    "HASR_Category_Rating": 4,
    "Overall_Star_Rating": 5,
    "Services_Offered": "Emergency Care\nImaging & Radiology\nOutpatient Surgery\nPediatric Services\nPharmacy\nPhysical Therapy\nRehabilitation"
  },
  {
    "Hospital_ID": 22,
    "Hospital_Name": "Elbert Memorial Hospital",
    "Street_Address": "4 Medical Dr",
    "City": "Elberton",
    "State": "GA",
    "ZIP_Code": "30635",
    "County": "Elbert County",
    "County_FIPS": "13105",
    "Latitude": 34.11332,
    "Longitude": -82.87487,
    "Urban_Rural": "Urban",
    "In_System": 0,
    "System_Name": "Elbert Memorial Hospital",
    "Ownership_Type": "Nonprofit",
    "Care_Level": "Primary",
    "Bed_Size": 25,
    "Size_Group": "S",
    "Hospital_URL": "https://www.google.com/search?q=Elbert+Memorial+Hospital+Elberton+GA+hospital",
    "Balance_Growth": 5,
    "Transparency": 5,
    "Fiscal_Health": 3,
    "Staffing": 3,
    "FTIH_Category_Rating": 4,
    "Tax_Benefit": 4,
    "Quality_of_CBS": 3,
    "Strategic_Use": 5,
    "CBS_Category_Rating": 5,
    "Financial_Burden": 4,
    "Charity_Care": 3,
    "Medical_Debt": 5,
    "HAB_Category_Rating": 3,
    "Range_of_Services": 5,
    "Demographic_Alignment": 3,
    "Workforce_Training": 4,
    "Pay_Equity_Ratio": 4,
    "HASR_Category_Rating": 4,
    "Overall_Star_Rating": 3,
    "Services_Offered": "Emergency Care\nImaging & Radiology\nOutpatient Surgery\nPharmacy\nPhysical Therapy\nRehabilitation"
  },
  {
    "Hospital_ID": 23,
    "Hospital_Name": "Emanuel Medical Center",
    "Street_Address": "117 Kite Rd",
    "City": "Swainsboro",
    "State": "GA",
    "ZIP_Code": "30401",
    "County": "Emanuel County",
    "County_FIPS": "13107",
    "Latitude": 32.59258,
    "Longitude": -82.34732,
    "Urban_Rural": "Urban",
    "In_System": 0,
    "System_Name": "Emanuel Medical Center",
    "Ownership_Type": "Nonprofit",
    "Care_Level": "Primary",
    "Bed_Size": 88,
    "Size_Group": "S",
    "Hospital_URL": "https://www.google.com/search?q=Emanuel+Medical+Center+Swainsboro+GA+hospital",
    "Balance_Growth": 4,
    "Transparency": 3,
    "Fiscal_Health": 4,
    "Staffing": 4,
    "FTIH_Category_Rating": 3,
    "Tax_Benefit": 4,
    "Quality_of_CBS": 3,
    "Strategic_Use": 5,
    "CBS_Category_Rating": 5,
    "Financial_Burden": 5,
    "Charity_Care": 3,
    "Medical_Debt": 4,
    "HAB_Category_Rating": 5,
    "Range_of_Services": 5,
    "Demographic_Alignment": 5,
    "Workforce_Training": 3,
    "Pay_Equity_Ratio": 4,
    "HASR_Category_Rating": 4,
    "Overall_Star_Rating": 5,
    "Services_Offered": "Emergency Care\nImaging & Radiology\nOutpatient Surgery\nOrthopedics\nPharmacy\nPhysical Therapy\nRehabilitation"
  },
  {
    "Hospital_ID": 24,
    "Hospital_Name": "Evans Memorial Hospital",
    "Street_Address": "200 N River St",
    "City": "Claxton",
    "State": "GA",
    "ZIP_Code": "30417",
    "County": "Evans County",
    "County_FIPS": "13109",
    "Latitude": 32.1589,
    "Longitude": -81.9043,
    "Urban_Rural": "Urban",
    "In_System": 0,
    "System_Name": "Evans Memorial Hospital",
    "Ownership_Type": "Nonprofit",
    "Care_Level": "Primary",
    "Bed_Size": 49,
    "Size_Group": "S",
    "Hospital_URL": "https://www.google.com/search?q=Evans+Memorial+Hospital+Claxton+GA+hospital",
    "Balance_Growth": 3,
    "Transparency": 4,
    "Fiscal_Health": 4,
    "Staffing": 3,
    "FTIH_Category_Rating": 4,
    "Tax_Benefit": 5,
    "Quality_of_CBS": 3,
    "Strategic_Use": 4,
    "CBS_Category_Rating": 5,
    "Financial_Burden": 5,
    "Charity_Care": 3,
    "Medical_Debt": 5,
    "HAB_Category_Rating": 5,
    "Range_of_Services": 5,
    "Demographic_Alignment": 5,
    "Workforce_Training": 5,
    "Pay_Equity_Ratio": 5,
    "HASR_Category_Rating": 4,
    "Overall_Star_Rating": 3,
    "Services_Offered": "Emergency Care\nImaging & Radiology\nOutpatient Surgery\nPharmacy\nPhysical Therapy\nRehabilitation"
  },
  {
    "Hospital_ID": 25,
    "Hospital_Name": "Irwin County Hospital",
    "Street_Address": "710 N Irwin Ave",
    "City": "Ocilla",
    "State": "GA",
    "ZIP_Code": "31774",
    "County": "Irwin County",
    "County_FIPS": "13155",
    "Latitude": 31.60329,
    "Longitude": -83.25134,
    "Urban_Rural": "Urban",
    "In_System": 0,
    "System_Name": "Irwin County Hospital",
    "Ownership_Type": "Nonprofit",
    "Care_Level": "Primary",
    "Bed_Size": 34,
    "Size_Group": "S",
    "Hospital_URL": "https://www.google.com/search?q=Irwin+County+Hospital+Ocilla+GA+hospital",
    "Balance_Growth": 5,
    "Transparency": 5,
    "Fiscal_Health": 3,
    "Staffing": 3,
    "FTIH_Category_Rating": 5,
    "Tax_Benefit": 5,
    "Quality_of_CBS": 4,
    "Strategic_Use": 5,
    "CBS_Category_Rating": 4,
    "Financial_Burden": 3,
    "Charity_Care": 4,
    "Medical_Debt": 4,
    "HAB_Category_Rating": 5,
    "Range_of_Services": 4,
    "Demographic_Alignment": 5,
    "Workforce_Training": 5,
    "Pay_Equity_Ratio": 3,
    "HASR_Category_Rating": 5,
    "Overall_Star_Rating": 3,
    "Services_Offered": "Emergency Care\nImaging & Radiology\nOutpatient Surgery\nPharmacy\nPhysical Therapy\nRehabilitation"
  },
  {
    "Hospital_ID": 26,
    "Hospital_Name": "Jasper Memorial Hospital",
    "Street_Address": "898 College St",
    "City": "Monticello",
    "State": "GA",
    "ZIP_Code": "31064",
    "County": "Jasper County",
    "County_FIPS": "13159",
    "Latitude": 33.31422,
    "Longitude": -83.6864,
    "Urban_Rural": "Urban",
    "In_System": 0,
    "System_Name": "Jasper Health Services, Inc.",
    "Ownership_Type": "Nonprofit",
    "Care_Level": "Primary",
    "Bed_Size": 17,
    "Size_Group": "S",
    "Hospital_URL": "https://www.google.com/search?q=Jasper+Memorial+Hospital+Monticello+GA+hospital",
    "Balance_Growth": 4,
    "Transparency": 5,
    "Fiscal_Health": 3,
    "Staffing": 5,
    "FTIH_Category_Rating": 5,
    "Tax_Benefit": 4,
    "Quality_of_CBS": 3,
    "Strategic_Use": 5,
    "CBS_Category_Rating": 4,
    "Financial_Burden": 5,
    "Charity_Care": 5,
    "Medical_Debt": 5,
    "HAB_Category_Rating": 4,
    "Range_of_Services": 4,
    "Demographic_Alignment": 4,
    "Workforce_Training": 5,
    "Pay_Equity_Ratio": 4,
    "HASR_Category_Rating": 4,
    "Overall_Star_Rating": 3,
    "Services_Offered": "Emergency Care\nImaging & Radiology\nOutpatient Surgery Pharmacy\nPhysical Therapy\nRehabilitation"
  },
  {
    "Hospital_ID": 27,
    "Hospital_Name": "Jeff Davis Hospital",
    "Street_Address": "163 S Tallahassee St",
    "City": "Hazlehurst",
    "State": "GA",
    "ZIP_Code": "31539",
    "County": "Jeff Davis County",
    "County_FIPS": "13161",
    "Latitude": 31.85727,
    "Longitude": -82.60728,
    "Urban_Rural": "Urban",
    "In_System": 0,
    "System_Name": "Jeff Davis Hospital",
    "Ownership_Type": "Nonprofit",
    "Care_Level": "Primary",
    "Bed_Size": 25,
    "Size_Group": "S",
    "Hospital_URL": "https://www.google.com/search?q=Jeff+Davis+Hospital+Hazlehurst+GA+hospital",
    "Balance_Growth": 5,
    "Transparency": 5,
    "Fiscal_Health": 4,
    "Staffing": 5,
    "FTIH_Category_Rating": 3,
    "Tax_Benefit": 4,
    "Quality_of_CBS": 3,
    "Strategic_Use": 3,
    "CBS_Category_Rating": 4,
    "Financial_Burden": 3,
    "Charity_Care": 3,
    "Medical_Debt": 4,
    "HAB_Category_Rating": 5,
    "Range_of_Services": 3,
    "Demographic_Alignment": 3,
    "Workforce_Training": 4,
    "Pay_Equity_Ratio": 5,
    "HASR_Category_Rating": 3,
    "Overall_Star_Rating": 5,
    "Services_Offered": "Emergency Care\nImaging & Radiology\nOutpatient Surgery\nPharmacy\nPhysical Therapy\nRehabilitation"
  },
  {
    "Hospital_ID": 28,
    "Hospital_Name": "Jefferson Hospital",
    "Street_Address": "1067 Peachtree St",
    "City": "Louisville",
    "State": "GA",
    "ZIP_Code": "30434",
    "County": "Jefferson County",
    "County_FIPS": "13163",
    "Latitude": 32.121,
    "Longitude": -82.412,
    "Urban_Rural": "Urban",
    "In_System": 0,
    "System_Name": "Jefferson Hospital",
    "Ownership_Type": "Nonprofit",
    "Care_Level": "Primary",
    "Bed_Size": 37,
    "Size_Group": "S",
    "Hospital_URL": "https://www.google.com/search?q=Jefferson+Hospital+Louisville+GA+hospital",
    "Balance_Growth": 5,
    "Transparency": 4,
    "Fiscal_Health": 3,
    "Staffing": 3,
    "FTIH_Category_Rating": 5,
    "Tax_Benefit": 3,
    "Quality_of_CBS": 3,
    "Strategic_Use": 5,
    "CBS_Category_Rating": 3,
    "Financial_Burden": 5,
    "Charity_Care": 4,
    "Medical_Debt": 5,
    "HAB_Category_Rating": 5,
    "Range_of_Services": 4,
    "Demographic_Alignment": 4,
    "Workforce_Training": 5,
    "Pay_Equity_Ratio": 3,
    "HASR_Category_Rating": 3,
    "Overall_Star_Rating": 4,
    "Services_Offered": "Emergency Care\nImaging & Radiology\nOutpatient Surgery\nPharmacy\nPhysical Therapy\nRehabilitation"
  },
  {
    "Hospital_ID": 29,
    "Hospital_Name": "Liberty Regional Medical Center",
    "Street_Address": "462 Elma G Miles Pkwy",
    "City": "Hinesville",
    "State": "GA",
    "ZIP_Code": "31313",
    "County": "Liberty County, Georgia",
    "County_FIPS": "13179",
    "Latitude": 31.8469,
    "Longitude": -81.5959,
    "Urban_Rural": "Urban",
    "In_System": 0,
    "System_Name": "Liberty Regional Medical Center",
    "Ownership_Type": "Nonprofit",
    "Care_Level": "Primary",
    "Bed_Size": 25,
    "Size_Group": "S",
    "Hospital_URL": "https://www.google.com/search?q=Liberty+Regional+Medical+Center+Hinesville+GA+hospital",
    "Balance_Growth": 4,
    "Transparency": 5,
    "Fiscal_Health": 3,
    "Staffing": 5,
    "FTIH_Category_Rating": 5,
    "Tax_Benefit": 4,
    "Quality_of_CBS": 5,
    "Strategic_Use": 4,
    "CBS_Category_Rating": 3,
    "Financial_Burden": 5,
    "Charity_Care": 3,
    "Medical_Debt": 4,
    "HAB_Category_Rating": 4,
    "Range_of_Services": 5,
    "Demographic_Alignment": 5,
    "Workforce_Training": 4,
    "Pay_Equity_Ratio": 5,
    "HASR_Category_Rating": 5,
    "Overall_Star_Rating": 3,
    "Services_Offered": "Cardiology\nEmergency Care\nImaging & Radiology\nMaternity & Neonatal ICU\nOrthopedics\nOutpatient Surgery\nPharmacy\nPhysical Therapy\nRehabilitation"
  },
  {
    "Hospital_ID": 30,
    "Hospital_Name": "Miller County Hospital",
    "Street_Address": "208 N Cuthbert St",
    "City": "Colquitt",
    "State": "GA",
    "ZIP_Code": "39837",
    "County": "Miller County",
    "County_FIPS": "13187",
    "Latitude": 31.1713,
    "Longitude": -84.7338,
    "Urban_Rural": "Urban",
    "In_System": 0,
    "System_Name": "Miller County Hospital",
    "Ownership_Type": "Nonprofit",
    "Care_Level": "Primary",
    "Bed_Size": 25,
    "Size_Group": "S",
    "Hospital_URL": "https://www.google.com/search?q=Miller+County+Hospital+Colquitt+GA+hospital",
    "Balance_Growth": 5,
    "Transparency": 4,
    "Fiscal_Health": 4,
    "Staffing": 4,
    "FTIH_Category_Rating": 5,
    "Tax_Benefit": 4,
    "Quality_of_CBS": 3,
    "Strategic_Use": 3,
    "CBS_Category_Rating": 4,
    "Financial_Burden": 5,
    "Charity_Care": 3,
    "Medical_Debt": 5,
    "HAB_Category_Rating": 5,
    "Range_of_Services": 5,
    "Demographic_Alignment": 5,
    "Workforce_Training": 3,
    "Pay_Equity_Ratio": 4,
    "HASR_Category_Rating": 4,
    "Overall_Star_Rating": 5,
    "Services_Offered": "Emergency Care\nImaging & Radiology\nOutpatient Surgery\nPharmacy\nPhysical Therapy\nRehabilitation"
  },
  {
    "Hospital_ID": 31,
    "Hospital_Name": "Monroe County Hospital",
    "Street_Address": "88 Martin Luther King Jr Dr",
    "City": "Forsyth",
    "State": "GA",
    "ZIP_Code": "31029",
    "County": "Monroe County",
    "County_FIPS": "13207",
    "Latitude": 33.0309,
    "Longitude": -83.945,
    "Urban_Rural": "Urban",
    "In_System": 0,
    "System_Name": "Monroe County Hospital",
    "Ownership_Type": "Nonprofit",
    "Care_Level": "Primary",
    "Bed_Size": 25,
    "Size_Group": "S",
    "Hospital_URL": "https://www.google.com/search?q=Monroe+County+Hospital+Forsyth+GA+hospital",
    "Balance_Growth": 4,
    "Transparency": 4,
    "Fiscal_Health": 3,
    "Staffing": 5,
    "FTIH_Category_Rating": 4,
    "Tax_Benefit": 5,
    "Quality_of_CBS": 3,
    "Strategic_Use": 4,
    "CBS_Category_Rating": 4,
    "Financial_Burden": 3,
    "Charity_Care": 5,
    "Medical_Debt": 3,
    "HAB_Category_Rating": 5,
    "Range_of_Services": 4,
    "Demographic_Alignment": 5,
    "Workforce_Training": 5,
    "Pay_Equity_Ratio": 5,
    "HASR_Category_Rating": 4,
    "Overall_Star_Rating": 3,
    "Services_Offered": "Emergency Care\nImaging & Radiology\nOutpatient Surgery\nPharmacy\nPhysical Therapy\nRehabilitation"
  },
  {
    "Hospital_ID": 32,
    "Hospital_Name": "Morgan Medical Center",
    "Street_Address": "1740 Lions Club Rd",
    "City": "Madison",
    "State": "GA",
    "ZIP_Code": "30650",
    "County": "Morgan County",
    "County_FIPS": "13189",
    "Latitude": 33.5849,
    "Longitude": -83.4807,
    "Urban_Rural": "Urban",
    "In_System": 0,
    "System_Name": "Morgan Medical Center",
    "Ownership_Type": "Nonprofit",
    "Care_Level": "Primary",
    "Bed_Size": 25,
    "Size_Group": "S",
    "Hospital_URL": "https://www.google.com/search?q=Morgan+Medical+Center+Madison+GA+hospital",
    "Balance_Growth": 4,
    "Transparency": 4,
    "Fiscal_Health": 3,
    "Staffing": 3,
    "FTIH_Category_Rating": 5,
    "Tax_Benefit": 5,
    "Quality_of_CBS": 5,
    "Strategic_Use": 4,
    "CBS_Category_Rating": 3,
    "Financial_Burden": 3,
    "Charity_Care": 5,
    "Medical_Debt": 3,
    "HAB_Category_Rating": 5,
    "Range_of_Services": 4,
    "Demographic_Alignment": 4,
    "Workforce_Training": 4,
    "Pay_Equity_Ratio": 3,
    "HASR_Category_Rating": 5,
    "Overall_Star_Rating": 5,
    "Services_Offered": "Cardiology\nEmergency Care\nImaging & Radiology\nOrthopedics\nOutpatient Surgery\nPharmacy\nPhysical Therapy\nRehabilitation"
  },
  {
    "Hospital_ID": 33,
    "Hospital_Name": "Shepherd Center",
    "Street_Address": "2020 Peachtree Rd NW",
    "City": "Atlanta",
    "State": "GA",
    "ZIP_Code": "30309",
    "County": "Fulton",
    "County_FIPS": "13121",
    "Latitude": 33.749,
    "Longitude": -84.388,
    "Urban_Rural": "Urban",
    "In_System": 0,
    "System_Name": "Shepherd Center",
    "Ownership_Type": "Nonprofit",
    "Care_Level": "Specialty",
    "Bed_Size": 152,
    "Size_Group": "L",
    "Hospital_URL": "https://www.google.com/search?q=Shepherd+Center+Atlanta+GA+hospital",
    "Balance_Growth": 5,
    "Transparency": 3,
    "Fiscal_Health": 5,
    "Staffing": 4,
    "FTIH_Category_Rating": 4,
    "Tax_Benefit": 4,
    "Quality_of_CBS": 3,
    "Strategic_Use": 5,
    "CBS_Category_Rating": 4,
    "Financial_Burden": 3,
    "Charity_Care": 4,
    "Medical_Debt": 3,
    "HAB_Category_Rating": 5,
    "Range_of_Services": 4,
    "Demographic_Alignment": 4,
    "Workforce_Training": 4,
    "Pay_Equity_Ratio": 4,
    "HASR_Category_Rating": 4,
    "Overall_Star_Rating": 3,
    "Services_Offered": "Behavioral Health\nImaging & Radiology\nPharmacy\nPhysical Therapy\nRehabilitation"
  },
  {
    "Hospital_ID": 34,
    "Hospital_Name": "Southwest Georgia Regional Medical Center",
    "Street_Address": "361 Randolph St",
    "City": "Cuthbert",
    "State": "GA",
    "ZIP_Code": "39840",
    "County": "Randolph County",
    "County_FIPS": "13243",
    "Latitude": 31.7716,
    "Longitude": -84.7887,
    "Urban_Rural": "Urban",
    "In_System": 0,
    "System_Name": "Southwest Georgia Health System",
    "Ownership_Type": "Nonprofit",
    "Care_Level": "Primary",
    "Bed_Size": 25,
    "Size_Group": "L",
    "Hospital_URL": "https://www.google.com/search?q=Southwest+Georgia+Regional+Medical+Center+Cuthbert+GA+hospital",
    "Balance_Growth": 4,
    "Transparency": 3,
    "Fiscal_Health": 4,
    "Staffing": 4,
    "FTIH_Category_Rating": 3,
    "Tax_Benefit": 4,
    "Quality_of_CBS": 3,
    "Strategic_Use": 4,
    "CBS_Category_Rating": 4,
    "Financial_Burden": 5,
    "Charity_Care": 4,
    "Medical_Debt": 3,
    "HAB_Category_Rating": 5,
    "Range_of_Services": 3,
    "Demographic_Alignment": 3,
    "Workforce_Training": 4,
    "Pay_Equity_Ratio": 3,
    "HASR_Category_Rating": 3,
    "Overall_Star_Rating": 5,
    "Services_Offered": "Emergency Care\nImaging & Radiology\nPharmacy\nPhysical Therapy\nRehabilitation"
  },
  {
    "Hospital_ID": 35,
    "Hospital_Name": "Stephens County Hospital",
    "Street_Address": "163 Hospital Dr",
    "City": "Toccoa",
    "State": "GA",
    "ZIP_Code": "30577",
    "County": "Stephens County",
    "County_FIPS": "13257",
    "Latitude": 34.5787,
    "Longitude": -83.3324,
    "Urban_Rural": "Urban",
    "In_System": 0,
    "System_Name": "Stephens County Hospital",
    "Ownership_Type": "Nonprofit",
    "Care_Level": "Primary",
    "Bed_Size": 96,
    "Size_Group": "S",
    "Hospital_URL": "https://www.google.com/search?q=Stephens+County+Hospital+Toccoa+GA+hospital",
    "Balance_Growth": 3,
    "Transparency": 4,
    "Fiscal_Health": 3,
    "Staffing": 3,
    "FTIH_Category_Rating": 4,
    "Tax_Benefit": 4,
    "Quality_of_CBS": 3,
    "Strategic_Use": 3,
    "CBS_Category_Rating": 3,
    "Financial_Burden": 4,
    "Charity_Care": 5,
    "Medical_Debt": 5,
    "HAB_Category_Rating": 5,
    "Range_of_Services": 3,
    "Demographic_Alignment": 3,
    "Workforce_Training": 3,
    "Pay_Equity_Ratio": 3,
    "HASR_Category_Rating": 5,
    "Overall_Star_Rating": 3,
    "Services_Offered": "Emergency Care\nImaging & Radiology\nOrthopedics\nOutpatient Surgery\nPharmacy\nPhysical Therapy\nRehabilitation"
  },
  {
    "Hospital_ID": 36,
    "Hospital_Name": "Taylor Regional Hospital",
    "Street_Address": "222 Perry Hwy",
    "City": "Hawkinsville",
    "State": "GA",
    "ZIP_Code": "31036",
    "County": "Taylor County",
    "County_FIPS": "13235",
    "Latitude": 32.4745,
    "Longitude": -83.7406,
    "Urban_Rural": "Urban",
    "In_System": 0,
    "System_Name": "Taylor Regional Hospital",
    "Ownership_Type": "Nonprofit",
    "Care_Level": "Specialty",
    "Bed_Size": 151,
    "Size_Group": "L",
    "Hospital_URL": "https://www.google.com/search?q=Taylor+Regional+Hospital+Hawkinsville+GA+hospital",
    "Balance_Growth": 3,
    "Transparency": 3,
    "Fiscal_Health": 5,
    "Staffing": 5,
    "FTIH_Category_Rating": 5,
    "Tax_Benefit": 5,
    "Quality_of_CBS": 4,
    "Strategic_Use": 3,
    "CBS_Category_Rating": 5,
    "Financial_Burden": 4,
    "Charity_Care": 4,
    "Medical_Debt": 3,
    "HAB_Category_Rating": 5,
    "Range_of_Services": 3,
    "Demographic_Alignment": 3,
    "Workforce_Training": 4,
    "Pay_Equity_Ratio": 4,
    "HASR_Category_Rating": 4,
    "Overall_Star_Rating": 5,
    "Services_Offered": "Cardiology\nEmergency Care\nImaging & Radiology\nOrthopedics\nOutpatient Surgery\nPharmacy\nPhysical Therapy\nRehabilitation"
  },
  {
    "Hospital_ID": 37,
    "Hospital_Name": "Tift Regional Medical Center",
    "Street_Address": "901 East 18th St",
    "City": "Tifton",
    "State": "GA",
    "ZIP_Code": "31794",
    "County": "Tift County",
    "County_FIPS": "13277",
    "Latitude": 31.4605,
    "Longitude": -83.5228,
    "Urban_Rural": "Urban",
    "In_System": 0,
    "System_Name": "Tift Regional Health System, Inc.",
    "Ownership_Type": "Nonprofit",
    "Care_Level": "Specialty",
    "Bed_Size": 181,
    "Size_Group": "XL",
    "Hospital_URL": "https://www.google.com/search?q=Tift+Regional+Medical+Center+Tifton+GA+hospital",
    "Balance_Growth": 5,
    "Transparency": 3,
    "Fiscal_Health": 5,
    "Staffing": 4,
    "FTIH_Category_Rating": 5,
    "Tax_Benefit": 5,
    "Quality_of_CBS": 4,
    "Strategic_Use": 3,
    "CBS_Category_Rating": 3,
    "Financial_Burden": 4,
    "Charity_Care": 4,
    "Medical_Debt": 5,
    "HAB_Category_Rating": 4,
    "Range_of_Services": 5,
    "Demographic_Alignment": 5,
    "Workforce_Training": 5,
    "Pay_Equity_Ratio": 3,
    "HASR_Category_Rating": 3,
    "Overall_Star_Rating": 4,
    "Services_Offered": "Behavioral Health\nCardiology\nEmergency Care\nImaging & Radiology\nMaternity & Neonatal ICU\nOncology\nOrthopedics\nOutpatient Surgery\nPediatric Services\nPharmacy\nPhysical Therapy\nRehabilitation"
  },
  {
    "Hospital_ID": 38,
    "Hospital_Name": "Upson Regional Medical Center",
    "Street_Address": "801 W Gordon St",
    "City": "Thomaston",
    "State": "GA",
    "ZIP_Code": "30286",
    "County": "Upson County",
    "County_FIPS": "13293",
    "Latitude": 32.8818,
    "Longitude": -84.3278,
    "Urban_Rural": "Urban",
    "In_System": 0,
    "System_Name": "Upson Regional Medical Center",
    "Ownership_Type": "Nonprofit",
    "Care_Level": "Primary",
    "Bed_Size": 115,
    "Size_Group": "L",
    "Hospital_URL": "https://www.google.com/search?q=Upson+Regional+Medical+Center+Thomaston+GA+hospital",
    "Balance_Growth": 5,
    "Transparency": 5,
    "Fiscal_Health": 4,
    "Staffing": 4,
    "FTIH_Category_Rating": 4,
    "Tax_Benefit": 5,
    "Quality_of_CBS": 3,
    "Strategic_Use": 4,
    "CBS_Category_Rating": 4,
    "Financial_Burden": 3,
    "Charity_Care": 4,
    "Medical_Debt": 5,
    "HAB_Category_Rating": 5,
    "Range_of_Services": 5,
    "Demographic_Alignment": 4,
    "Workforce_Training": 5,
    "Pay_Equity_Ratio": 5,
    "HASR_Category_Rating": 5,
    "Overall_Star_Rating": 5,
    "Services_Offered": "Cardiology\nEmergency Care\nImaging & Radiology\nOrthopedics\nOutpatient Surgery\nPediatric Services\nPharmacy\nPhysical Therapy\nRehabilitation"
  },
  {
    "Hospital_ID": 39,
    "Hospital_Name": "Warm Springs Medical Center",
    "Street_Address": "5995 Spring St",
    "City": "Warm Springs",
    "State": "GA",
    "ZIP_Code": "31830",
    "County": "Meriwether County",
    "County_FIPS": "13189",
    "Latitude": 32.8944,
    "Longitude": -84.6786,
    "Urban_Rural": "Urban",
    "In_System": 0,
    "System_Name": "Warm Springs Medical Center",
    "Ownership_Type": "Nonprofit",
    "Care_Level": "Primary",
    "Bed_Size": 104,
    "Size_Group": "L",
    "Hospital_URL": "https://www.google.com/search?q=Warm+Springs+Medical+Center+Warm+Springs+GA+hospital",
    "Balance_Growth": 3,
    "Transparency": 3,
    "Fiscal_Health": 4,
    "Staffing": 4,
    "FTIH_Category_Rating": 5,
    "Tax_Benefit": 3,
    "Quality_of_CBS": 4,
    "Strategic_Use": 4,
    "CBS_Category_Rating": 5,
    "Financial_Burden": 5,
    "Charity_Care": 3,
    "Medical_Debt": 5,
    "HAB_Category_Rating": 4,
    "Range_of_Services": 3,
    "Demographic_Alignment": 4,
    "Workforce_Training": 4,
    "Pay_Equity_Ratio": 3,
    "HASR_Category_Rating": 5,
    "Overall_Star_Rating": 4,
    "Services_Offered": "Emergency Care\nImaging & Radiology\nPharmacy\nPhysical Therapy\nRehabilitation"
  },
  {
    "Hospital_ID": 40,
    "Hospital_Name": "Washington County Regional Medical Center",
    "Street_Address": "610 Sparta Rd",
    "City": "Sandersville",
    "State": "GA",
    "ZIP_Code": "31082",
    "County": "Washington County",
    "County_FIPS": "13181",
    "Latitude": 32.9956,
    "Longitude": -82.8044,
    "Urban_Rural": "Urban",
    "In_System": 0,
    "System_Name": "Washington County Regional Medical Center",
    "Ownership_Type": "Nonprofit",
    "Care_Level": "Primary",
    "Bed_Size": 56,
    "Size_Group": "S",
    "Hospital_URL": "https://www.google.com/search?q=Washington+County+Regional+Medical+Center+Sandersville+GA+hospital",
    "Balance_Growth": 4,
    "Transparency": 5,
    "Fiscal_Health": 5,
    "Staffing": 4,
    "FTIH_Category_Rating": 4,
    "Tax_Benefit": 4,
    "Quality_of_CBS": 5,
    "Strategic_Use": 5,
    "CBS_Category_Rating": 4,
    "Financial_Burden": 5,
    "Charity_Care": 3,
    "Medical_Debt": 3,
    "HAB_Category_Rating": 5,
    "Range_of_Services": 4,
    "Demographic_Alignment": 5,
    "Workforce_Training": 3,
    "Pay_Equity_Ratio": 5,
    "HASR_Category_Rating": 4,
    "Overall_Star_Rating": 5,
    "Services_Offered": "Emergency Care\nImaging & Radiology\nOrthopedics\nOutpatient Surgery\nPharmacy\nPhysical Therapy\nRehabilitation"
  },
  {
    "Hospital_ID": 41,
    "Hospital_Name": "Hamilton Medical Center",
    "Street_Address": "1200 MEMORIAL DRIVE",
    "City": "Dalton",
    "State": "GA",
    "ZIP_Code": "30720",
    "County": "Whitfield County",
    "County_FIPS": "13313",
    "Latitude": 34.7889,
    "Longitude": -84.985,
    "Urban_Rural": "Urban",
    "In_System": 1,
    "System_Name": "Hamilton Health Care System",
    "Ownership_Type": "Non-profit",
    "Care_Level": "Acute Care",
    "Bed_Size": 177,
    "Size_Group": "L",
    "Hospital_URL": "https://www.google.com/search?q=Hamilton+Medical+Center+Dalton+GA+hospital",
    "Balance_Growth": 3,
    "Transparency": 3,
    "Fiscal_Health": 5,
    "Staffing": 3,
    "FTIH_Category_Rating": 3,
    "Tax_Benefit": 3,
    "Quality_of_CBS": 4,
    "Strategic_Use": 3,
    "CBS_Category_Rating": 3,
    "Financial_Burden": 3,
    "Charity_Care": 3,
    "Medical_Debt": 3,
    "HAB_Category_Rating": 4,
    "Range_of_Services": 5,
    "Demographic_Alignment": 3,
    "Workforce_Training": 4,
    "Pay_Equity_Ratio": 4,
    "HASR_Category_Rating": 3,
    "Overall_Star_Rating": 4,
    "Services_Offered": "Behavioral Health\nCardiology\nEmergency Care\nImaging & Radiology\nMaternity & Neonatal ICU\nOncology\nOrthopedics\nOutpatient Surgery\nPediatric Services\nPharmacy\nPhysical Therapy\nRehabilitation"
  },
  {
    "Hospital_ID": 42,
    "Hospital_Name": "Memorial Satilla Health",
    "Street_Address": "1900 TEBEAU STREET",
    "City": "Waycross",
    "State": "GA",
    "ZIP_Code": "31501",
    "County": "Ware County",
    "County_FIPS": "13305",
    "Latitude": 31.2249,
    "Longitude": -82.348,
    "Urban_Rural": "Urban",
    "In_System": 1,
    "System_Name": "HCA Healthcare",
    "Ownership_Type": "Non-profit",
    "Care_Level": "Acute Care",
    "Bed_Size": 345,
    "Size_Group": "XXL",
    "Hospital_URL": "https://www.google.com/search?q=Memorial+Satilla+Health+Waycross+GA+hospital",
    "Balance_Growth": 3,
    "Transparency": 3,
    "Fiscal_Health": 4,
    "Staffing": 3,
    "FTIH_Category_Rating": 3,
    "Tax_Benefit": 5,
    "Quality_of_CBS": 5,
    "Strategic_Use": 3,
    "CBS_Category_Rating": 4,
    "Financial_Burden": 4,
    "Charity_Care": 4,
    "Medical_Debt": 5,
    "HAB_Category_Rating": 3,
    "Range_of_Services": 3,
    "Demographic_Alignment": 3,
    "Workforce_Training": 3,
    "Pay_Equity_Ratio": 3,
    "HASR_Category_Rating": 3,
    "Overall_Star_Rating": 3,
    "Services_Offered": "Behavioral Health\nCardiology\nEmergency Care\nImaging & Radiology\nMaternity & Neonatal ICU\nOncology\nOrthopedics\nOutpatient Surgery\nPediatric Services\nPharmacy\nPhysical Therapy\nRehabilitation"
  },
  {
    "Hospital_ID": 43,
    "Hospital_Name": "Northside Hospital Forsyth",
    "Street_Address": "1200 NORTHSIDE FORSYTH DRIVE",
    "City": "Cumming",
    "State": "GA",
    "ZIP_Code": "30041",
    "County": "Forsyth",
    "County_FIPS": "13117",
    "Latitude": 34.2073,
    "Longitude": -84.1402,
    "Urban_Rural": "Urban",
    "In_System": 1,
    "System_Name": "Northside Hospital System",
    "Ownership_Type": "Non-profit",
    "Care_Level": "Acute Care",
    "Bed_Size": 181,
    "Size_Group": "L",
    "Hospital_URL": "https://www.google.com/search?q=Northside+Hospital+Forsyth+Cumming+GA+hospital",
    "Balance_Growth": 4,
    "Transparency": 4,
    "Fiscal_Health": 4,
    "Staffing": 4,
    "FTIH_Category_Rating": 4,
    "Tax_Benefit": 4,
    "Quality_of_CBS": 4,
    "Strategic_Use": 4,
    "CBS_Category_Rating": 3,
    "Financial_Burden": 3,
    "Charity_Care": 3,
    "Medical_Debt": 4,
    "HAB_Category_Rating": 3,
    "Range_of_Services": 4,
    "Demographic_Alignment": 3,
    "Workforce_Training": 5,
    "Pay_Equity_Ratio": 3,
    "HASR_Category_Rating": 3,
    "Overall_Star_Rating": 3,
    "Services_Offered": "Behavioral Health\nCardiology\nEmergency Care\nImaging & Radiology\nMaternity & Neonatal ICU\nOncology\nOrthopedics\nOutpatient Surgery\nPediatric Services\nPharmacy\nPhysical Therapy\nRehabilitation"
  },
  {
    "Hospital_ID": 44,
    "Hospital_Name": "Northside Hospital Cherokee",
    "Street_Address": "450 NORTHSIDE CHEROKEE BOULEVARD",
    "City": "Canton",
    "State": "GA",
    "ZIP_Code": "30115",
    "County": "Cherokee",
    "County_FIPS": "13057",
    "Latitude": 34.2368,
    "Longitude": -84.4908,
    "Urban_Rural": "Urban",
    "In_System": 1,
    "System_Name": "Northside Hospital System",
    "Ownership_Type": "Non-profit",
    "Care_Level": "Acute Care",
    "Bed_Size": 146,
    "Size_Group": "L",
    "Hospital_URL": "https://www.google.com/search?q=Northside+Hospital+Cherokee+Canton+GA+hospital",
    "Balance_Growth": 3,
    "Transparency": 3,
    "Fiscal_Health": 4,
    "Staffing": 4,
    "FTIH_Category_Rating": 3,
    "Tax_Benefit": 3,
    "Quality_of_CBS": 3,
    "Strategic_Use": 4,
    "CBS_Category_Rating": 3,
    "Financial_Burden": 5,
    "Charity_Care": 5,
    "Medical_Debt": 4,
    "HAB_Category_Rating": 3,
    "Range_of_Services": 3,
    "Demographic_Alignment": 3,
    "Workforce_Training": 3,
    "Pay_Equity_Ratio": 5,
    "HASR_Category_Rating": 4,
    "Overall_Star_Rating": 4,
    "Services_Offered": "Behavioral Health\nCardiology\nEmergency Care\nImaging & Radiology\nMaternity & Neonatal ICU\nOncology\nOrthopedics\nOutpatient Surgery\nPediatric Services\nPharmacy\nPhysical Therapy\nRehabilitation"
  },
  {
    "Hospital_ID": 45,
    "Hospital_Name": "Tanner Medical Center - Carrollton",
    "Street_Address": "705 DIXIE STREET",
    "City": "Carrollton",
    "State": "GA",
    "ZIP_Code": "30117",
    "County": "Carroll County",
    "County_FIPS": "13045",
    "Latitude": 33.5707,
    "Longitude": -85.0732,
    "Urban_Rural": "Urban",
    "In_System": 1,
    "System_Name": "Tanner Health System",
    "Ownership_Type": "Non-profit",
    "Care_Level": "Acute Care",
    "Bed_Size": 263,
    "Size_Group": "XL",
    "Hospital_URL": "https://www.google.com/search?q=Tanner+Medical+Center+-+Carrollton+Carrollton+GA+hospital",
    "Balance_Growth": 4,
    "Transparency": 3,
    "Fiscal_Health": 4,
    "Staffing": 4,
    "FTIH_Category_Rating": 3,
    "Tax_Benefit": 4,
    "Quality_of_CBS": 3,
    "Strategic_Use": 4,
    "CBS_Category_Rating": 3,
    "Financial_Burden": 4,
    "Charity_Care": 4,
    "Medical_Debt": 5,
    "HAB_Category_Rating": 4,
    "Range_of_Services": 3,
    "Demographic_Alignment": 4,
    "Workforce_Training": 5,
    "Pay_Equity_Ratio": 4,
    "HASR_Category_Rating": 4,
    "Overall_Star_Rating": 4,
    "Services_Offered": "Behavioral Health\nCardiology\nEmergency Care\nImaging & Radiology\nMaternity & Neonatal ICU\nOncology\nOrthopedics\nOutpatient Surgery\nPediatric Services\nPharmacy\nPhysical Therapy\nRehabilitation"
  },
  {
    "Hospital_ID": 46,
    "Hospital_Name": "Tanner Medical Center - Villa Rica",
    "Street_Address": "601 DALLAS HIGHWAY",
    "City": "Villa Rica",
    "State": "GA",
    "ZIP_Code": "30180",
    "County": "Carroll County",
    "County_FIPS": "13045",
    "Latitude": 33.7324,
    "Longitude": -84.919,
    "Urban_Rural": "Urban",
    "In_System": 1,
    "System_Name": "Tanner Health System",
    "Ownership_Type": "Non-profit",
    "Care_Level": "Acute Care",
    "Bed_Size": 95,
    "Size_Group": "L",
    "Hospital_URL": "https://www.google.com/search?q=Tanner+Medical+Center+-+Villa+Rica+Villa+Rica+GA+hospital",
    "Balance_Growth": 5,
    "Transparency": 5,
    "Fiscal_Health": 3,
    "Staffing": 3,
    "FTIH_Category_Rating": 3,
    "Tax_Benefit": 4,
    "Quality_of_CBS": 3,
    "Strategic_Use": 5,
    "CBS_Category_Rating": 4,
    "Financial_Burden": 4,
    "Charity_Care": 4,
    "Medical_Debt": 4,
    "HAB_Category_Rating": 3,
    "Range_of_Services": 3,
    "Demographic_Alignment": 3,
    "Workforce_Training": 3,
    "Pay_Equity_Ratio": 3,
    "HASR_Category_Rating": 3,
    "Overall_Star_Rating": 3,
    "Services_Offered": "Behavioral Health\nCardiology\nEmergency Care\nImaging & Radiology\nMaternity & Neonatal ICU\nOncology\nOrthopedics\nOutpatient Surgery\nPediatric Services\nPharmacy\nPhysical Therapy\nRehabilitation"
  },
  {
    "Hospital_ID": 47,
    "Hospital_Name": "Wellstar West Georgia Medical Center",
    "Street_Address": "1514 VERNON ROAD",
    "City": "Lagrange",
    "State": "GA",
    "ZIP_Code": "30240",
    "County": "Troup",
    "County_FIPS": "13285",
    "Latitude": 33.0454,
    "Longitude": -85.031,
    "Urban_Rural": "Urban",
    "In_System": 1,
    "System_Name": "Wellstar Health System",
    "Ownership_Type": "Non-profit",
    "Care_Level": "Acute Care",
    "Bed_Size": 177,
    "Size_Group": "L",
    "Hospital_URL": "https://www.google.com/search?q=Wellstar+West+Georgia+Medical+Center+Lagrange+GA+hospital",
    "Balance_Growth": 3,
    "Transparency": 3,
    "Fiscal_Health": 5,
    "Staffing": 3,
    "FTIH_Category_Rating": 3,
    "Tax_Benefit": 5,
    "Quality_of_CBS": 3,
    "Strategic_Use": 4,
    "CBS_Category_Rating": 3,
    "Financial_Burden": 3,
    "Charity_Care": 4,
    "Medical_Debt": 3,
    "HAB_Category_Rating": 3,
    "Range_of_Services": 3,
    "Demographic_Alignment": 3,
    "Workforce_Training": 3,
    "Pay_Equity_Ratio": 5,
    "HASR_Category_Rating": 3,
    "Overall_Star_Rating": 4,
    "Services_Offered": "Behavioral Health\nCardiology\nEmergency Care\nImaging & Radiology\nMaternity & Neonatal ICU\nOncology\nOrthopedics\nOutpatient Surgery\nPediatric Services\nPharmacy\nPhysical Therapy\nRehabilitation"
  },
  {
    "Hospital_ID": 48,
    "Hospital_Name": "Piedmont Newton",
    "Street_Address": "5126 HOSPITAL DRIVE NE",
    "City": "Covington",
    "State": "GA",
    "ZIP_Code": "30014",
    "County": "Newton County",
    "County_FIPS": "13217",
    "Latitude": 33.6018,
    "Longitude": -83.8487,
    "Urban_Rural": "Urban",
    "In_System": 1,
    "System_Name": "Piedmont Healthcare",
    "Ownership_Type": "Non-profit",
    "Care_Level": "Acute Care",
    "Bed_Size": 196,
    "Size_Group": "XL",
    "Hospital_URL": "https://www.google.com/search?q=Piedmont+Newton+Covington+GA+hospital",
    "Balance_Growth": 5,
    "Transparency": 3,
    "Fiscal_Health": 4,
    "Staffing": 3,
    "FTIH_Category_Rating": 3,
    "Tax_Benefit": 4,
    "Quality_of_CBS": 3,
    "Strategic_Use": 5,
    "CBS_Category_Rating": 3,
    "Financial_Burden": 3,
    "Charity_Care": 3,
    "Medical_Debt": 3,
    "HAB_Category_Rating": 4,
    "Range_of_Services": 4,
    "Demographic_Alignment": 3,
    "Workforce_Training": 3,
    "Pay_Equity_Ratio": 5,
    "HASR_Category_Rating": 4,
    "Overall_Star_Rating": 3,
    "Services_Offered": "Behavioral Health\nCardiology\nEmergency Care\nImaging & Radiology\nMaternity & Neonatal ICU\nOncology\nOrthopedics\nOutpatient Surgery\nPediatric Services\nPharmacy\nPhysical Therapy Rehabilitation"
  },
  {
    "Hospital_ID": 49,
    "Hospital_Name": "AdventHealth Gordon",
    "Street_Address": "1035 RED BUD ROAD",
    "City": "Calhoun",
    "State": "GA",
    "ZIP_Code": "30701",
    "County": "Gordon County",
    "County_FIPS": "13129",
    "Latitude": 34.5103,
    "Longitude": -84.931,
    "Urban_Rural": "Urban",
    "In_System": 1,
    "System_Name": "AdventHealth",
    "Ownership_Type": "Non-profit",
    "Care_Level": "Acute Care",
    "Bed_Size": 289,
    "Size_Group": "xl",
    "Hospital_URL": "https://www.google.com/search?q=AdventHealth+Gordon+Calhoun+GA+hospital",
    "Balance_Growth": 4,
    "Transparency": 4,
    "Fiscal_Health": 3,
    "Staffing": 4,
    "FTIH_Category_Rating": 4,
    "Tax_Benefit": 4,
    "Quality_of_CBS": 3,
    "Strategic_Use": 4,
    "CBS_Category_Rating": 4,
    "Financial_Burden": 3,
    "Charity_Care": 4,
    "Medical_Debt": 4,
    "HAB_Category_Rating": 3,
    "Range_of_Services": 4,
    "Demographic_Alignment": 3,
    "Workforce_Training": 4,
    "Pay_Equity_Ratio": 3,
    "HASR_Category_Rating": 3,
    "Overall_Star_Rating": 3,
    "Services_Offered": "Behavioral Health\nCardiology\nEmergency Care\nImaging & Radiology\nMaternity & Neonatal ICU\nOncology\nOrthopedics\nOutpatient Surgery\nPediatric Services\nPharmacy\nPhysical Therapy\nRehabilitation"
  },
  {
    "Hospital_ID": 50,
    "Hospital_Name": "Candler Hospital",
    "Street_Address": "5353 REYNOLDS STREET",
    "City": "Savannah",
    "State": "GA",
    "ZIP_Code": "31412",
    "County": "Chatham",
    "County_FIPS": "13051",
    "Latitude": 32.0809,
    "Longitude": -81.0912,
    "Urban_Rural": "Urban",
    "In_System": 1,
    "System_Name": "St. Joseph\u2019s / Candler Health System",
    "Ownership_Type": "Non-profit",
    "Care_Level": "Acute Care",
    "Bed_Size": 162,
    "Size_Group": "L",
    "Hospital_URL": "https://www.google.com/search?q=Candler+Hospital+Savannah+GA+hospital",
    "Balance_Growth": 4,
    "Transparency": 3,
    "Fiscal_Health": 3,
    "Staffing": 3,
    "FTIH_Category_Rating": 3,
    "Tax_Benefit": 4,
    "Quality_of_CBS": 3,
    "Strategic_Use": 4,
    "CBS_Category_Rating": 4,
    "Financial_Burden": 4,
    "Charity_Care": 4,
    "Medical_Debt": 3,
    "HAB_Category_Rating": 3,
    "Range_of_Services": 4,
    "Demographic_Alignment": 4,
    "Workforce_Training": 4,
    "Pay_Equity_Ratio": 5,
    "HASR_Category_Rating": 3,
    "Overall_Star_Rating": 3,
    "Services_Offered": "Behavioral Health\nCardiology\nEmergency Care\nImaging & Radiology\nMaternity & Neonatal ICU\nOncology\nOrthopedics\nOutpatient Surgery\nPediatric Services\nPharmacy\nPhysical Therapy\nRehabilitation"
  }
]